[{"code":"BLM","name":"Saint Barthélemy","name_zh":"圣巴泰勒米","name_local":"Saint-Barthélemy","short_name":"Saint Barthelemy","level":0,"level_name":"Country","parent_code":null,"source":"geonames"},{"code":"BLM.1_1","name":"AuVent","name_zh":null,"name_local":null,"short_name":"AuVent","level":1,"level_name":"Paroisse","parent_code":"BLM","source":"gadm"},{"code":"BLM.2_1","name":"SousleVent","name_zh":null,"name_local":null,"short_name":"SousleVent","level":1,"level_name":"Paroisse","parent_code":"BLM","source":"gadm"},{"code":"BLM.2.2_1","name":"AnsedesCayes","name_zh":null,"name_local":null,"short_name":"AnsedesCayes","level":2,"level_name":"Quartier","parent_code":"BLM.2_1","source":"gadm"},{"code":"BLM.2.3_1","name":"AnsedesLézards","name_zh":null,"name_local":null,"short_name":"AnsedesLézards","level":2,"level_name":"Quartier","parent_code":"BLM.2_1","source":"gadm"},{"code":"BLM.1.1_1","name":"AnseduGouverneur","name_zh":null,"name_local":null,"short_name":"AnseduGouverneur","level":2,"level_name":"Quartier","parent_code":"BLM.1_1","source":"gadm"},{"code":"BLM.1.2_1","name":"AnseduGrandCul-de-Sac","name_zh":null,"name_local":null,"short_name":"AnseduGrandCul-de-Sac","level":2,"level_name":"Quartier","parent_code":"BLM.1_1","source":"gadm"},{"code":"BLM.2.1_1","name":"Aéroport","name_zh":null,"name_local":null,"short_name":"Aéroport","level":2,"level_name":"Quartier","parent_code":"BLM.2_1","source":"gadm"},{"code":"BLM.1.3_1","name":"BarrièredesQuatresVents","name_zh":null,"name_local":null,"short_name":"BarrièredesQuatresVents","level":2,"level_name":"Quartier","parent_code":"BLM.1_1","source":"gadm"},{"code":"BLM.1.4_1","name":"Camaruche","name_zh":null,"name_local":null,"short_name":"Camaruche","level":2,"level_name":"Quartier","parent_code":"BLM.1_1","source":"gadm"},{"code":"BLM.2.4_1","name":"Carénage","name_zh":null,"name_local":null,"short_name":"Carénage","level":2,"level_name":"Quartier","parent_code":"BLM.2_1","source":"gadm"},{"code":"BLM.2.5_1","name":"ColdelaTourmente","name_zh":null,"name_local":null,"short_name":"ColdelaTourmente","level":2,"level_name":"Quartier","parent_code":"BLM.2_1","source":"gadm"},{"code":"BLM.2.6_1","name":"Colombier","name_zh":null,"name_local":null,"short_name":"Colombier","level":2,"level_name":"Quartier","parent_code":"BLM.2_1","source":"gadm"},{"code":"BLM.2.7_1","name":"Corossol","name_zh":null,"name_local":null,"short_name":"Corossol","level":2,"level_name":"Quartier","parent_code":"BLM.2_1","source":"gadm"},{"code":"BLM.1.5_1","name":"Devet","name_zh":null,"name_local":null,"short_name":"Devet","level":2,"level_name":"Quartier","parent_code":"BLM.1_1","source":"gadm"},{"code":"BLM.2.8_1","name":"Flamands","name_zh":null,"name_local":null,"short_name":"Flamands","level":2,"level_name":"Quartier","parent_code":"BLM.2_1","source":"gadm"},{"code":"BLM.1.6_1","name":"Gouverneur","name_zh":null,"name_local":null,"short_name":"Gouverneur","level":2,"level_name":"Quartier","parent_code":"BLM.1_1","source":"gadm"},{"code":"BLM.1.7_1","name":"GrandCul-de-Sac","name_zh":null,"name_local":null,"short_name":"GrandCul-de-Sac","level":2,"level_name":"Quartier","parent_code":"BLM.1_1","source":"gadm"},{"code":"BLM.1.8_1","name":"GrandFond","name_zh":null,"name_local":null,"short_name":"GrandFond","level":2,"level_name":"Quartier","parent_code":"BLM.1_1","source":"gadm"},{"code":"BLM.1.9_1","name":"GrandeSaline","name_zh":null,"name_local":null,"short_name":"GrandeSaline","level":2,"level_name":"Quartier","parent_code":"BLM.1_1","source":"gadm"},{"code":"BLM.2.9_1","name":"GrandeVigie","name_zh":null,"name_local":null,"short_name":"GrandeVigie","level":2,"level_name":"Quartier","parent_code":"BLM.2_1","source":"gadm"},{"code":"BLM.2.10_1","name":"Gustavia","name_zh":null,"name_local":null,"short_name":"Gustavia","level":2,"level_name":"Quartier","parent_code":"BLM.2_1","source":"gadm"},{"code":"BLM.1.10_1","name":"Isles","name_zh":null,"name_local":null,"short_name":"Isles","level":2,"level_name":"Quartier","parent_code":"BLM.1_1","source":"gadm"},{"code":"BLM.2.11_1","name":"Isles","name_zh":null,"name_local":null,"short_name":"Isles","level":2,"level_name":"Quartier","parent_code":"BLM.2_1","source":"gadm"},{"code":"BLM.2.12_1","name":"LaGrandeMontagne","name_zh":null,"name_local":null,"short_name":"LaGrandeMontagne","level":2,"level_name":"Quartier","parent_code":"BLM.2_1","source":"gadm"},{"code":"BLM.2.13_1","name":"LaPointe","name_zh":null,"name_local":null,"short_name":"LaPointe","level":2,"level_name":"Quartier","parent_code":"BLM.2_1","source":"gadm"},{"code":"BLM.2.14_1","name":"LeChâteau","name_zh":null,"name_local":null,"short_name":"LeChâteau","level":2,"level_name":"Quartier","parent_code":"BLM.2_1","source":"gadm"},{"code":"BLM.2.15_1","name":"LePalidor","name_zh":null,"name_local":null,"short_name":"LePalidor","level":2,"level_name":"Quartier","parent_code":"BLM.2_1","source":"gadm"},{"code":"BLM.1.11_1","name":"Lorient","name_zh":null,"name_local":null,"short_name":"Lorient","level":2,"level_name":"Quartier","parent_code":"BLM.1_1","source":"gadm"},{"code":"BLM.2.16_1","name":"Lurin","name_zh":null,"name_local":null,"short_name":"Lurin","level":2,"level_name":"Quartier","parent_code":"BLM.2_1","source":"gadm"},{"code":"BLM.1.12_1","name":"Marigot","name_zh":null,"name_local":null,"short_name":"Marigot","level":2,"level_name":"Quartier","parent_code":"BLM.1_1","source":"gadm"},{"code":"BLM.2.17_1","name":"Merlette","name_zh":null,"name_local":null,"short_name":"Merlette","level":2,"level_name":"Quartier","parent_code":"BLM.2_1","source":"gadm"},{"code":"BLM.1.13_1","name":"MontJean","name_zh":null,"name_local":null,"short_name":"MontJean","level":2,"level_name":"Quartier","parent_code":"BLM.1_1","source":"gadm"},{"code":"BLM.1.14_1","name":"MorneCriquet","name_zh":null,"name_local":null,"short_name":"MorneCriquet","level":2,"level_name":"Quartier","parent_code":"BLM.1_1","source":"gadm"},{"code":"BLM.1.16_1","name":"MorneRouge","name_zh":null,"name_local":null,"short_name":"MorneRouge","level":2,"level_name":"Quartier","parent_code":"BLM.1_1","source":"gadm"},{"code":"BLM.1.15_1","name":"MornedeDépoudré","name_zh":null,"name_local":null,"short_name":"MornedeDépoudré","level":2,"level_name":"Quartier","parent_code":"BLM.1_1","source":"gadm"},{"code":"BLM.1.17_1","name":"PetitCul-de-Sac","name_zh":null,"name_local":null,"short_name":"PetitCul-de-Sac","level":2,"level_name":"Quartier","parent_code":"BLM.1_1","source":"gadm"},{"code":"BLM.1.18_1","name":"PetiteSaline","name_zh":null,"name_local":null,"short_name":"PetiteSaline","level":2,"level_name":"Quartier","parent_code":"BLM.1_1","source":"gadm"},{"code":"BLM.1.19_1","name":"PointeMilou","name_zh":null,"name_local":null,"short_name":"PointeMilou","level":2,"level_name":"Quartier","parent_code":"BLM.1_1","source":"gadm"},{"code":"BLM.2.18_1","name":"Public","name_zh":null,"name_local":null,"short_name":"Public","level":2,"level_name":"Quartier","parent_code":"BLM.2_1","source":"gadm"},{"code":"BLM.2.19_1","name":"QuartierduRoi","name_zh":null,"name_local":null,"short_name":"QuartierduRoi","level":2,"level_name":"Quartier","parent_code":"BLM.2_1","source":"gadm"},{"code":"BLM.2.20_1","name":"Saint-Jean","name_zh":null,"name_local":null,"short_name":"Saint-Jean","level":2,"level_name":"Quartier","parent_code":"BLM.2_1","source":"gadm"},{"code":"BLM.2.21_1","name":"TerreNeuve","name_zh":null,"name_local":null,"short_name":"TerreNeuve","level":2,"level_name":"Quartier","parent_code":"BLM.2_1","source":"gadm"},{"code":"BLM.1.20_1","name":"Toiny","name_zh":null,"name_local":null,"short_name":"Toiny","level":2,"level_name":"Quartier","parent_code":"BLM.1_1","source":"gadm"},{"code":"BLM.1.21_1","name":"Vitet","name_zh":null,"name_local":null,"short_name":"Vitet","level":2,"level_name":"Quartier","parent_code":"BLM.1_1","source":"gadm"}]