[{"code":"PYF","name":"French Polynesia","name_zh":"法属波利尼西亚","name_local":"Polynésie française","short_name":"French Polynesia","level":0,"level_name":"Country","parent_code":null,"source":"geonames"},{"code":"PYF.1_1","name":"ÎlesAustrales","name_zh":null,"name_local":null,"short_name":"ÎlesAustrales","level":1,"level_name":"Subdivisionsadministratives","parent_code":"PYF","source":"gadm"},{"code":"PYF.3_1","name":"ÎlesMarquises","name_zh":null,"name_local":null,"short_name":"ÎlesMarquises","level":1,"level_name":"Subdivisionsadministratives","parent_code":"PYF","source":"gadm"},{"code":"PYF.4_1","name":"ÎlesSous-le-Vent","name_zh":null,"name_local":null,"short_name":"ÎlesSous-le-Vent","level":1,"level_name":"Subdivisionsadministratives","parent_code":"PYF","source":"gadm"},{"code":"PYF.5_1","name":"ÎlesTuamotu-Gambier","name_zh":null,"name_local":null,"short_name":"ÎlesTuamotu-Gambier","level":1,"level_name":"Subdivisionsadministratives","parent_code":"PYF","source":"gadm"},{"code":"PYF.2_1","name":"ÎlesduVent","name_zh":null,"name_local":null,"short_name":"ÎlesduVent","level":1,"level_name":"Subdivisionsadministratives","parent_code":"PYF","source":"gadm"}]